valette/__init__.py
valette/dom.py
valette/expr.py
valette/mesh.py
valette/valette.cp311-win_amd64.pyd
valette-0.1.0.data/data/README/README.md
valette-0.1.0.data/data/licenses/APACHE2
valette-0.1.0.data/data/licenses/MIT
valette-0.1.0.dist-info/LICENSE
valette-0.1.0.dist-info/METADATA
valette-0.1.0.dist-info/WHEEL
valette-0.1.0.dist-info/top_level.txt
valette-0.1.0.dist-info/RECORD
